COPYING
COPYING.lesser
MANIFEST.in
NOTICE
README.md
requirements.txt
setup.py
compiler/__init__.py
compiler/api/__init__.py
compiler/api/compiler.py
compiler/api/source/auth_key.tl
compiler/api/source/main_api.tl
compiler/api/source/sys_msgs.tl
compiler/api/template/combinator.txt
compiler/api/template/type.txt
compiler/docs/__init__.py
compiler/docs/compiler.py
compiler/docs/template/page.txt
compiler/docs/template/toctree.txt
compiler/errors/__init__.py
compiler/errors/compiler.py
compiler/errors/sort.py
compiler/errors/source/303_SEE_OTHER.tsv
compiler/errors/source/400_BAD_REQUEST.tsv
compiler/errors/source/401_UNAUTHORIZED.tsv
compiler/errors/source/403_FORBIDDEN.tsv
compiler/errors/source/406_NOT_ACCEPTABLE.tsv
compiler/errors/source/420_FLOOD.tsv
compiler/errors/source/500_INTERNAL_SERVER_ERROR.tsv
compiler/errors/source/503_SERVICE_UNAVAILABLE.tsv
compiler/errors/template/class.txt
compiler/errors/template/sub_class.txt
pov/__init__.py
pov/assistant.py
pov/client.py
pov/dispatcher.py
pov/emoji.py
pov/file_id.py
pov/filters.py
pov/mime_types.py
pov/py.typed
pov/sync.py
pov/utils.py
pov.egg-info/PKG-INFO
pov.egg-info/SOURCES.txt
pov.egg-info/dependency_links.txt
pov.egg-info/requires.txt
pov.egg-info/top_level.txt
pov.egg-info/zip-safe
pov/connection/__init__.py
pov/connection/connection.py
pov/connection/transport/__init__.py
pov/connection/transport/tcp/__init__.py
pov/connection/transport/tcp/tcp.py
pov/connection/transport/tcp/tcp_abridged.py
pov/connection/transport/tcp/tcp_abridged_o.py
pov/connection/transport/tcp/tcp_full.py
pov/connection/transport/tcp/tcp_intermediate.py
pov/connection/transport/tcp/tcp_intermediate_o.py
pov/crypto/__init__.py
pov/crypto/aes.py
pov/crypto/mtproto.py
pov/crypto/prime.py
pov/crypto/rsa.py
pov/enums/__init__.py
pov/enums/auto_name.py
pov/enums/chat_action.py
pov/enums/chat_event_action.py
pov/enums/chat_member_status.py
pov/enums/chat_members_filter.py
pov/enums/chat_type.py
pov/enums/message_entity_type.py
pov/enums/message_media_type.py
pov/enums/message_service_type.py
pov/enums/messages_filter.py
pov/enums/next_code_type.py
pov/enums/parse_mode.py
